account/__init__.py
account/info.py
bursts/__init__.py
bursts/query.py
imagery/__init__.py
imagery/fix.py
imagery/processing.py
imagery/query.py
imagery/untitled.py
util/__init__.py
util/geo.py
util/optical_flow.py
util/rag.py
util/rag2.py
util/stitching.py
hivemapper_python-0.4.17.dist-info/METADATA
hivemapper_python-0.4.17.dist-info/WHEEL
hivemapper_python-0.4.17.dist-info/top_level.txt
hivemapper_python-0.4.17.dist-info/RECORD
