Metadata-Version: 2.4
Name: hivemapper-python
Version: 0.4.17
Summary: SDK for Hivemapper APIs
Author-email: Hivemapper <hi@hivemapper.com>
Project-URL: Homepage, https://github.com/Hivemapper/hive-py
Project-URL: Issues, https://github.com/Hivemapper/hive-py/issues
Classifier: Programming Language :: Python :: 3
Classifier: License :: OSI Approved :: MIT License
Classifier: Operating System :: OS Independent
Requires-Python: >=3.10
Requires-Dist: area==1.1.1
Requires-Dist: geographiclib>=2.0
Requires-Dist: geopy>=2.3.0
Requires-Dist: numpy
Requires-Dist: opencv-python>=4.10
Requires-Dist: pyexiftool==0.5.6
Requires-Dist: pyproj>=3.7.0
Requires-Dist: pyshp>=2.3.1
Requires-Dist: requests>=2.31.0
Requires-Dist: scipy>=1.14.1
Requires-Dist: shapely>=2.0.1
Requires-Dist: tqdm>=4.66.1
Requires-Dist: timezonefinder>=6.2.0
Requires-Dist: python-dateutil
